<xml xmlns="https://developers.google.com/blockly/xml"><block type="component_event" id="baxCm#WgX-j43v=1Hm^e" x="148" y="89"><mutation xmlns="http://www.w3.org/1999/xhtml" component_name="Sign out" component_type="Button" parent_id="undefined" event_id="Click" was_updated="true"/><field name="component_id">7f70a39f-d480-4e63-a2dd-0434da3cf7d4</field><field name="event_id">Click</field><statement name="input_do"><block type="signin_sign_out_advanced" id="{k,v7Zh(4RMFf/1i{-ev" inline="false"><mutation xmlns="http://www.w3.org/1999/xhtml" show_callback_params="true" callback_params_added="true"/><value name="CALLBACK_PARAM0"><block type="callback_arg" id="!$cY;YNM7b,|QhJqW2,^"><mutation xmlns="http://www.w3.org/1999/xhtml" tooltip="" language_neutral_name="error" arg_name_trans_key="blocks.signin.error" old_arg_name="error"/></block></value><statement name="DO"><block type="controls_if" id="Yre2SlJmb=(P^~QT/mby"><mutation else="1"/><value name="IF0"><block type="callback_arg" id="HGO/Ff=PDs@Fy`zWD_tE"><mutation xmlns="http://www.w3.org/1999/xhtml" tooltip="" language_neutral_name="error" arg_name_trans_key="blocks.signin.error" old_arg_name="error" is_detached_parameter="true"/></block></value><statement name="DO0"><block type="setter" id="3)Qr,P+Cv36W;t#4vRV+"><mutation xmlns="http://www.w3.org/1999/xhtml" component_name="Label1"/><field name="component_id">Label1</field><field name="field_name">Text</field><value name="field_value"><shadow type="text" id="P|aOvzc/{;zy,q87^Ua}"><field name="TEXT">Label</field></shadow><block type="callback_arg" id="C,JpHXyqk3Zb;Tv:fSAi"><mutation xmlns="http://www.w3.org/1999/xhtml" tooltip="" language_neutral_name="error" arg_name_trans_key="blocks.signin.error" old_arg_name="error" is_detached_parameter="true"/></block></value></block></statement><statement name="ELSE"><block type="controls_navigate_new" id="M|aBCVql~2JcHZbwfhIu"><value name="COMPONENT"><shadow type="any_component_component_dropdown" id="ketkOqs6sFL|Ss6!u}=%"><mutation xmlns="http://www.w3.org/1999/xhtml" component_id="Sign In/Up Screen" component_types_to_include="[&quot;Screen&quot;]"/><field name="component_id">1c553deb-af71-4c26-96e9-3b08bb079615</field></shadow></value></block></statement></block></statement></block></statement></block><block type="component_event" id="dU?/K,g4QD+%WoeQcfzg" x="608" y="91"><mutation xmlns="http://www.w3.org/1999/xhtml" component_name="cancel button" component_type="Button" parent_id="undefined" event_id="Click" was_updated="true"/><field name="component_id">47771b38-006a-4e2b-bf01-62ff24473c0e</field><field name="event_id">Click</field><statement name="input_do"><block type="controls_navigate_new" id="yobV.!Fc{QM4+{}5YC;Z"><value name="COMPONENT"><shadow type="any_component_component_dropdown" id="mG!0I)sf58wb[T~;5_?n"><mutation xmlns="http://www.w3.org/1999/xhtml" component_id="Profile" component_types_to_include="[&quot;Screen&quot;]"/><field name="component_id">0eb93835-0d35-4799-8d01-fbb9c16ab870</field></shadow></value></block></statement></block><block type="component_event" id="By-zA7c~4`@vgSg^tty:" x="150" y="322"><mutation xmlns="http://www.w3.org/1999/xhtml" component_name="Reset Password" component_type="Button" parent_id="undefined" event_id="Click" was_updated="true"/><field name="component_id">16882052-cc3e-4338-a704-811c8ca47f9d</field><field name="event_id">Click</field><statement name="input_do"><block type="signin_reset_password_advanced" id="T,udW7C|Fbz}Pq?/qcy$" inline="false"><mutation xmlns="http://www.w3.org/1999/xhtml" show_callback_params="true" callback_params_added="true"/><value name="EMAIL"><shadow type="text" id="nFT}CEFrCPINa1q|HqQk"><field name="TEXT">hello@gmail.com</field></shadow><block type="variables_get" id="t.|~s6f~;1w0kN8GPdNJ"><mutation xmlns="http://www.w3.org/1999/xhtml" saved_name="app variable email session"/><field name="VAR">a7407c1c-1dd8-434f-8a82-5d9614cf7ff6</field></block></value><value name="CALLBACK_PARAM0"><block type="callback_arg" id="2{[T{PHb9286up_H6Wd7"><mutation xmlns="http://www.w3.org/1999/xhtml" tooltip="" language_neutral_name="error" arg_name_trans_key="blocks.signin.error" old_arg_name="error"/></block></value><statement name="DO"><block type="controls_if" id="Rk0J(x6k7gF(Kq74?Sa|"><mutation else="1"/><value name="IF0"><block type="callback_arg" id="fj@.%$a=lWe.ats|96@R"><mutation xmlns="http://www.w3.org/1999/xhtml" tooltip="" language_neutral_name="error" arg_name_trans_key="blocks.signin.error" old_arg_name="error" is_detached_parameter="true"/></block></value><statement name="DO0"><block type="setter" id="5^|BhFtzQ*Oyo;^6/uHJ"><mutation xmlns="http://www.w3.org/1999/xhtml" component_name="Label1"/><field name="component_id">Label1</field><field name="field_name">Text</field><value name="field_value"><shadow type="text" id="P|aOvzc/{;zy,q87^Ua}"><field name="TEXT">Label</field></shadow><block type="callback_arg" id="Hs])9Cs?JJ6Ik./I~dmB"><mutation xmlns="http://www.w3.org/1999/xhtml" tooltip="" language_neutral_name="error" arg_name_trans_key="blocks.signin.error" old_arg_name="error" is_detached_parameter="true"/></block></value></block></statement><statement name="ELSE"><block type="setter" id="/LT,/mA!S,|R#nnMkj~!"><mutation xmlns="http://www.w3.org/1999/xhtml" component_name="Label1"/><field name="component_id">Label1</field><field name="field_name">Text</field><value name="field_value"><shadow type="text" id="P|aOvzc/{;zy,q87^Ua}"><field name="TEXT">Label</field></shadow><block type="text_join" id="tAap/(_D9HS#oUK(d-90"><mutation items="2"/><value name="ADD0"><block type="text" id="+,}aiL:gW5FYC^a-|,VR"><field name="TEXT">Reset Password sent to email:</field></block></value><value name="ADD1"><block type="variables_get" id="^^NtZSll_U,|cI:(46s4"><mutation xmlns="http://www.w3.org/1999/xhtml" saved_name="app variable email session"/><field name="VAR">a7407c1c-1dd8-434f-8a82-5d9614cf7ff6</field></block></value></block></value></block></statement></block></statement></block></statement></block></xml>